pyroll/byon_lee_wear_model/__init__.py
pyroll/byon_lee_wear_model/report.py
pyroll/byon_lee_wear_model/roll_pass.py
pyroll_byon_lee_wear_model-3.0.0a0.dist-info/METADATA
pyroll_byon_lee_wear_model-3.0.0a0.dist-info/WHEEL
pyroll_byon_lee_wear_model-3.0.0a0.dist-info/licenses/LICENSE
pyroll_byon_lee_wear_model-3.0.0a0.dist-info/RECORD
