Metadata-Version: 2.4
Name: pyroll-byon-lee-wear-model
Version: 3.0.0a0
Summary: Plugin for PyRolL providing the Wear model of Byon and Lee.
Project-URL: Homepage, https://pyroll.readthedocs.io
Project-URL: Repository, https://github.com/pyroll-project/pyroll-byon-lee-wear-model
Project-URL: Documentation, https://github.com/pyroll-project/pyroll-byon-lee-wear-model/blob/main/docs/docs.pdf
Author-email: Christoph Renzing <christoph.renzing@imf.tu-freiberg.de>
License-Expression: BSD-3-Clause
License-File: LICENSE
Classifier: Development Status :: 5 - Production/Stable
Classifier: Framework :: Hatch
Classifier: Framework :: IPython
Classifier: Framework :: Jupyter
Classifier: Framework :: Pytest
Classifier: Framework :: Sphinx
Classifier: Intended Audience :: Manufacturing
Classifier: Intended Audience :: Science/Research
Classifier: License :: OSI Approved :: BSD License
Classifier: Natural Language :: English
Classifier: Operating System :: OS Independent
Classifier: Programming Language :: Python :: 3
Classifier: Programming Language :: Python :: 3.9
Classifier: Programming Language :: Python :: 3.10
Classifier: Programming Language :: Python :: 3.11
Classifier: Topic :: Scientific/Engineering
Requires-Python: <4.0,>=3.9
Requires-Dist: pyroll-core~=3.0
Requires-Dist: pyroll-profile-bulging~=3.0
